{
  "title": "Skyline Stretch",
  "saveAndShareEtsyLink": "https://infinitybeardesigns.etsy.com/ca/listing/4474002393/skyline-stretch-modern-cross-stitch",
  "etsyLink": "",
  "itchioLink": "https://infinity-bear-designs.itch.io/skyline-stretch-cross-stitch",
  "slug": "skyline-stretch-cross-stitch",
  "details": [
    {
      "label": "DMC Floss",
      "info": "13 colours"
    },
    {
      "label": "Pattern Size",
      "info": " 60w x 60h stitches"
    },
    {
      "label": "Completed Size",
      "info": "4.3 x 4.3 inches or 10.9 x 10.9 cm on 14 count aida"
    }
  ],
  "descriptionType": "Pattern",
  "story": "The kitty lazily stretches in front of the skyscraper and gently bats at the windows, softly meowing for yummy treats and head scritches."
}
