{
    "title":  "The Constellation Witch",
    "saveAndShareEtsyLink":  "",
    "etsyLink":  "",
    "itchioLink":  "https://infinity-bear-designs.itch.io/the-constellation-witch-cross-stitch",
    "slug":  "the-constellation-witch-cross-stitch",
    "story": "On her celestial canvas, she pens tales with starlit stokes, each story frolicking freely in the boundless playground of the universe.",
    "details":  [
                    {
                        "label":  "DMC Floss",
                        "info":  "5 colours"
                    },
                    {
                        "label":  "Pattern Size",
                        "info":  "92 x 95 stitches"
                    },
                    {
                        "label":  "Completed Size",
                        "info":  "7.14 x 7.14 in or 18.14 x 18.14 cm on 14 count aida"
                    }
                ],
    "descriptionType":  "Pattern"
}
