{
	"descriptionType": "STL",
	"details": [
		{
			"info": "Floss Drop",
			"label": "Type"
		},
		{
			"info": "46.8mm x 52.2mm x 1.0mm",
			"label": "Dimensions"
		},
		{
			"info": "3D Printing",
			"label": "Used For"
		}
	],
	"saveAndShareEtsyLink": "https://infinitybeardesigns.etsy.com/ca/listing/1423649256/shooting-star-decorative-cross-stitch?utm_source=Copy&utm_medium=ListingManager&utm_campaign=Share&utm_term=so.lmsm&share_time=1694271169248",
    "directEtsyLink": "https://www.etsy.com/ca/listing/1423649256/shooting-star-decorative-cross-stitch",
	"itchioLink": "https://infinity-bear-designs.itch.io/shooting-star-stl",
	"slug": "shooting-star-stl",
	"title": "Shooting Star STL"
}